jsonformer/__init__.py
jsonformer/format.py
jsonformer/logits_processors.py
jsonformer/main.py
jsonformer_450-0.12.0.dist-info/license.txt
jsonformer_450-0.12.0.dist-info/METADATA
jsonformer_450-0.12.0.dist-info/WHEEL
jsonformer_450-0.12.0.dist-info/RECORD
