Metadata-Version: 2.3
Name: jsonformer-450
Version: 0.12.0
Summary: This is a fix to the jsonformer package, allowing compatibility with transformers 4.50.0
Author: 1rgs
Author-email: rgsduke@gmail.com
Requires-Python: >=3.8,<4.0
Classifier: Programming Language :: Python :: 3
Classifier: Programming Language :: Python :: 3.8
Classifier: Programming Language :: Python :: 3.9
Classifier: Programming Language :: Python :: 3.10
Classifier: Programming Language :: Python :: 3.11
Classifier: Programming Language :: Python :: 3.12
Classifier: Programming Language :: Python :: 3.13
Requires-Dist: termcolor (>=2.3.0,<3.0.0)
